[
  {
    "pageName": "Ametiszt Ruhatisztító",
    "data": {
      "Image": { "source": "", "alt": "", "class": "" },
      "Introduction": {
        "p1": "A Bio Barát Biobolt egy 11 éve sikeresen működő, és folyamatosan bővülő bolthálózat, melyet magas szakmai tudással rendelkező magyar tulajdonosok hoztak létre. A Bio Barát Biobolt első sorban magasan minősítetttermékeivel, szakeladóival, köztük számos ismert természetgyógyásszal és fito-terapeutával jeleskedik a piacon. Folyamatosan bővülő termékpalettánkon olyan minőségi élelmiszereket és étrend-kiegészítőket sorakoztatunk csak fel, amely emelik ezen piac színvonalát, így azon vásárlók igényeit is igyekszünk kielégíteni, akik speciális táplálkozás irányt követnek.",
        "p2": "",
        "p3": "",
        "p4": "",
        "p5": "",
        "p6": ""
      },
      "Lists": {
        "List1": { "listName:": "", "listItems": {} },
        "List2": { "listName:": "", "listItems": {} },
        "List3": { "listName:": "", "listItems": {} },
        "List4": { "listName:": "", "listItems": {} },
        "List5": { "listName:": "", "listItems": {} }
      }
    }
  }
]
